moviestory/__init__.py
moviestory/main.py
moviestory-0.0.1.dist-info/LICENSE
moviestory-0.0.1.dist-info/METADATA
moviestory-0.0.1.dist-info/WHEEL
moviestory-0.0.1.dist-info/top_level.txt
moviestory-0.0.1.dist-info/zip-safe
moviestory-0.0.1.dist-info/RECORD
